cocoserver/__init__.py
cocoserver/__main__.py
cocoserver-1.0.9.dist-info/LICENSE
cocoserver-1.0.9.dist-info/METADATA
cocoserver-1.0.9.dist-info/WHEEL
cocoserver-1.0.9.dist-info/entry_points.txt
cocoserver-1.0.9.dist-info/top_level.txt
cocoserver-1.0.9.dist-info/RECORD
