Metadata-Version: 2.1
Name: cocoserver
Version: 1.0.9
Summary: A local HTTP server for compressed content.
Author-email: Marc Culler <culler@users.noreply.github.com>, "Nathan M. Dunfield" <nathan@dunfield.info>, Matthias Görner <enischte@gmail.com>
Maintainer-email: Marc Culler <culler@users.noreply.github.com>, "Nathan M. Dunfield" <nathan@dunfield.info>, Matthias Görner <enischte@gmail.com>
Project-URL: Homepage, https://github.com/3-manifolds/cocoserver
Project-URL: Bug Tracker, https://github.com/3-manifolds/cocoserver/issues
Keywords: http,server,gzip,documentation
Classifier: Development Status :: 3 - Alpha
Classifier: Intended Audience :: Developers
Classifier: License :: OSI Approved :: GNU General Public License v2 or later (GPLv2+)
Classifier: Operating System :: OS Independent
Classifier: Programming Language :: Python
Classifier: Topic :: Software Development :: Documentation
Requires-Python: >=3.8
License-File: LICENSE
